replace_null.py
stats_models.py
replace_null-2.0.2.dist-info/LICENSE
replace_null-2.0.2.dist-info/METADATA
replace_null-2.0.2.dist-info/WHEEL
replace_null-2.0.2.dist-info/top_level.txt
replace_null-2.0.2.dist-info/RECORD
