Metadata-Version: 2.1
Name: replace-null
Version: 2.0.2
Summary: A small example package
Home-page: UNKNOWN
Author: Lalu Prasad Mahto
Author-email: lalumahato020@gmail.com
License: UNKNOWN
Platform: UNKNOWN
Classifier: Programming Language :: Python :: 3
Classifier: License :: OSI Approved :: MIT License
Classifier: Operating System :: OS Independent
Requires-Python: >=3.6
License-File: LICENSE
Requires-Dist: statsmodels
